ifcfg/__init__.py
ifcfg/cli.py
ifcfg/parser.py
ifcfg/tools.py
ifcfg-0.23.dist-info/LICENSE
ifcfg-0.23.dist-info/METADATA
ifcfg-0.23.dist-info/WHEEL
ifcfg-0.23.dist-info/entry_points.txt
ifcfg-0.23.dist-info/namespace_packages.txt
ifcfg-0.23.dist-info/top_level.txt
ifcfg-0.23.dist-info/RECORD
